{"is_source_file": false, "format": "", "description": "", "external_files": [], "external_methods": [], "published": [], "classes": [], "methods": [], "calls": [], "search-terms": [], "state": 2, "file_id": 1, "knowledge_revision": 17, "git_revision": "83e2c2aaa5550d2c7ac9d38f7e2e9d44639fd4e6", "hash": "16df4da927d239ad4ef0193d4d0b8b7a", "format-version": 4, "code-base-name": "tic_tac_toe_frontend", "filename": "README.md", "revision_history": [{"17": "83e2c2aaa5550d2c7ac9d38f7e2e9d44639fd4e6"}]}